doms_databasen/__init__.py
doms_databasen/_constants.py
doms_databasen/_exceptions.py
doms_databasen/_text_extraction.py
doms_databasen/_utils.py
doms_databasen/_xpaths.py
doms_databasen/processor.py
doms_databasen/scraper.py
doms_databasen-0.2.0.dist-info/LICENSE
doms_databasen-0.2.0.dist-info/METADATA
doms_databasen-0.2.0.dist-info/WHEEL
doms_databasen-0.2.0.dist-info/RECORD
