Metadata-Version: 2.1
Name: doms_databasen
Version: 0.2.0
Summary: Scraper and PDF text processor for domsdatabasen.dk
License: MIT
Author: Oliver Kinch
Author-email: oliver.kinch@alexandra.dk
Requires-Python: >=3.10,<3.13
Classifier: License :: OSI Approved :: MIT License
Classifier: Programming Language :: Python :: 3
Classifier: Programming Language :: Python :: 3.10
Classifier: Programming Language :: Python :: 3.11
Classifier: Programming Language :: Python :: 3.12
Requires-Dist: datasets (>=2.17.1,<3.0.0)
Requires-Dist: easyocr (>=1.7.1,<2.0.0)
Requires-Dist: hydra-core (>=1.3.2,<2.0.0)
Requires-Dist: img2table (>=1.2.11,<2.0.0)
Requires-Dist: jsonlines (>=4.0.0,<5.0.0)
Requires-Dist: numpy (>=1.26.4,<2.0.0)
Requires-Dist: omegaconf (>=2.3.0,<3.0.0)
Requires-Dist: pdf2image (>=1.17.0,<2.0.0)
Requires-Dist: poppler-utils (>=0.1.0,<0.2.0)
Requires-Dist: pypdf (>=4.0.2,<5.0.0)
Requires-Dist: scikit-image (>=0.22.0,<0.23.0)
Requires-Dist: selenium (>=4.18.1,<5.0.0)
Requires-Dist: tabulate (>=0.9.0,<0.10.0)
Requires-Dist: tika (>=2.6.0,<3.0.0)
Requires-Dist: webdriver-manager (>=4.0.1,<5.0.0)
